filtertree/__init__.py
filtertree/cli.py
filtertree-0.2.0.dist-info/LICENSE.txt
filtertree-0.2.0.dist-info/METADATA
filtertree-0.2.0.dist-info/WHEEL
filtertree-0.2.0.dist-info/entry_points.txt
filtertree-0.2.0.dist-info/RECORD
