Metadata-Version: 2.1
Name: filtertree
Version: 0.2.0
Summary: Apply a filter to the directory tree
Home-page: https://github.com/takatoh/filtertree
License: MIT
Author: takatoh
Author-email: takatoh.m@gmail.com
Requires-Python: >=3.10,<4.0
Classifier: License :: OSI Approved :: MIT License
Classifier: Programming Language :: Python :: 3
Classifier: Programming Language :: Python :: 3.10
Classifier: Programming Language :: Python :: 3.11
Classifier: Programming Language :: Python :: 3.12
Classifier: Programming Language :: Python :: 3.13
Project-URL: Repository, https://github.com/takatoh/filtertree
